{"data": {"id": 209766, "dateTime": "2025-08-09T15:30:00Z", "lastCalculationDate": "2025-10-16T07:57:01.234284Z", "iterationId": 1422, "squadHome": {"id": 1260, "players": [{"id": 965, "shirtNumber": 37}, {"id": 15629, "shirtNumber": 2}, {"id": 19637, "shirtNumber": 29}, {"id": 29299, "shirtNumber": 27}, {"id": 30547, "shirtNumber": 1}, {"id": 34417, "shirtNumber": 77}, {"id": 38322, "shirtNumber": 10}, {"id": 39923, "shirtNumber": 18}, {"id": 41253, "shirtNumber": 23}, {"id": 52605, "shirtNumber": 8}, {"id": 57425, "shirtNumber": 11}, {"id": 66949, "shirtNumber": 33}, {"id": 67246, "shirtNumber": 99}, {"id": 73989, "shirtNumber": 14}, {"id": 87562, "shirtNumber": 9}, {"id": 89237, "shirtNumber": 22}, {"id": 115920, "shirtNumber": 80}, {"id": 158542, "shirtNumber": 4}, {"id": 276067, "shirtNumber": 17}, {"id": 276070, "shirtNumber": 35}], "startingPositions": [{"playerId": 965, "position": "CENTRAL_MIDFIELD", "positionSide": "CENTRE_RIGHT"}, {"playerId": 15629, "position": "RIGHT_WINGBACK_DEFENDER", "positionSide": "RIGHT"}, {"playerId": 19637, "position": "CENTRAL_DEFENDER", "positionSide": "CENTRE_RIGHT"}, {"playerId": 34417, "position": "GOALKEEPER", "positionSide": "CENTRE"}, {"playerId": 39923, "position": "CENTRAL_DEFENDER", "positionSide": "CENTRE_LEFT"}, {"playerId": 52605, "position": "CENTRAL_MIDFIELD", "positionSide": "CENTRE_LEFT"}, {"playerId": 57425, "position": "LEFT_WINGER", "positionSide": "LEFT"}, {"playerId": 66949, "position": "LEFT_WINGBACK_DEFENDER", "positionSide": "LEFT"}, {"playerId": 89237, "position": "CENTER_FORWARD", "positionSide": "CENTRE"}, {"playerId": 276067, "position": "RIGHT_WINGER", "positionSide": "RIGHT"}, {"playerId": 276070, "position": "DEFENSE_MIDFIELD", "positionSide": "CENTRE"}], "substitutions": [{"gameTime": {"gameTime": "65:18.6460", "gameTimeInSec": 11218.646}, "playerId": 29299, "toPosition": "LEFT_WINGER", "positionSide": "LEFT", "fromPosition": "BANK", "fromPositionSide": "UNKNOWN", "exchangedPlayerId": 57425, "substitutionType": "SUB_ON"}, {"gameTime": {"gameTime": "65:18.6460", "gameTimeInSec": 11218.646}, "playerId": 57425, "toPosition": "BANK", "positionSide": "UNKNOWN", "fromPosition": "LEFT_WINGER", "fromPositionSide": "LEFT", "exchangedPlayerId": 29299, "substitutionType": "SUB_OFF"}, {"gameTime": {"gameTime": "65:18.6460", "gameTimeInSec": 11218.646}, "playerId": 67246, "toPosition": "CENTER_FORWARD", "positionSide": "CENTRE", "fromPosition": "BANK", "fromPositionSide": "UNKNOWN", "exchangedPlayerId": 89237, "substitutionType": "SUB_ON"}, {"gameTime": {"gameTime": "65:18.6460", "gameTimeInSec": 11218.646}, "playerId": 87562, "toPosition": "RIGHT_WINGER", "positionSide": "RIGHT", "fromPosition": "BANK", "fromPositionSide": "UNKNOWN", "exchangedPlayerId": 276067, "substitutionType": "SUB_ON"}, {"gameTime": {"gameTime": "65:18.6460", "gameTimeInSec": 11218.646}, "playerId": 89237, "toPosition": "BANK", "positionSide": "UNKNOWN", "fromPosition": "CENTER_FORWARD", "fromPositionSide": "CENTRE", "exchangedPlayerId": 67246, "substitutionType": "SUB_OFF"}, {"gameTime": {"gameTime": "65:18.6460", "gameTimeInSec": 11218.646}, "playerId": 276067, "toPosition": "BANK", "positionSide": "UNKNOWN", "fromPosition": "RIGHT_WINGER", "fromPositionSide": "RIGHT", "exchangedPlayerId": 87562, "substitutionType": "SUB_OFF"}, {"gameTime": {"gameTime": "73:06.3280", "gameTimeInSec": 11686.328}, "playerId": 965, "toPosition": "BANK", "positionSide": "UNKNOWN", "fromPosition": "CENTRAL_MIDFIELD", "fromPositionSide": "CENTRE_RIGHT", "exchangedPlayerId": 38322, "substitutionType": "SUB_OFF"}, {"gameTime": {"gameTime": "73:06.3280", "gameTimeInSec": 11686.328}, "playerId": 38322, "toPosition": "CENTRAL_MIDFIELD", "positionSide": "CENTRE_LEFT", "fromPosition": "BANK", "fromPositionSide": "UNKNOWN", "exchangedPlayerId": 965, "substitutionType": "SUB_ON"}, {"gameTime": {"gameTime": "73:06.3280", "gameTimeInSec": 11686.328}, "playerId": 52605, "toPosition": "CENTRAL_MIDFIELD", "positionSide": "CENTRE_RIGHT", "fromPosition": "CENTRAL_MIDFIELD", "fromPositionSide": "CENTRE_LEFT", "exchangedPlayerId": null, "substitutionType": "POSITION_SIDE_CHANGE"}, {"gameTime": {"gameTime": "87:14.3270", "gameTimeInSec": 12534.327}, "playerId": 41253, "toPosition": "DEFENSE_MIDFIELD", "positionSide": "CENTRE", "fromPosition": "BANK", "fromPositionSide": "UNKNOWN", "exchangedPlayerId": 276070, "substitutionType": "SUB_ON"}, {"gameTime": {"gameTime": "87:14.3270", "gameTimeInSec": 12534.327}, "playerId": 276070, "toPosition": "BANK", "positionSide": "UNKNOWN", "fromPosition": "DEFENSE_MIDFIELD", "fromPositionSide": "CENTRE", "exchangedPlayerId": 41253, "substitutionType": "SUB_OFF"}], "startingFormation": "4-3-3", "formations": [{"gameTime": "00:00.0000", "gameTimeInSec": 0.0, "formation": "4-3-3"}], "coachId": 5517}, "squadAway": {"id": 1830, "players": [{"id": 262, "shirtNumber": 11}, {"id": 609, "shirtNumber": 28}, {"id": 4082, "shirtNumber": 9}, {"id": 6922, "shirtNumber": 8}, {"id": 14982, "shirtNumber": 77}, {"id": 20014, "shirtNumber": 32}, {"id": 30666, "shirtNumber": 99}, {"id": 39845, "shirtNumber": 22}, {"id": 40371, "shirtNumber": 14}, {"id": 49346, "shirtNumber": 19}, {"id": 53196, "shirtNumber": 7}, {"id": 56070, "shirtNumber": 31}, {"id": 56367, "shirtNumber": 61}, {"id": 67636, "shirtNumber": 4}, {"id": 68270, "shirtNumber": 18}, {"id": 74053, "shirtNumber": 6}, {"id": 107198, "shirtNumber": 17}, {"id": 109851, "shirtNumber": 13}, {"id": 137991, "shirtNumber": 10}, {"id": 187079, "shirtNumber": 20}, {"id": 215731, "shirtNumber": 2}, {"id": 218537, "shirtNumber": 35}, {"id": 278396, "shirtNumber": 12}], "startingPositions": [{"playerId": 262, "position": "LEFT_WINGER", "positionSide": "LEFT"}, {"playerId": 609, "position": "RIGHT_WINGBACK_DEFENDER", "positionSide": "RIGHT"}, {"playerId": 4082, "position": "CENTER_FORWARD", "positionSide": "CENTRE"}, {"playerId": 6922, "position": "CENTRAL_MIDFIELD", "positionSide": "CENTRE_RIGHT"}, {"playerId": 39845, "position": "CENTRAL_DEFENDER", "positionSide": "CENTRE_RIGHT"}, {"playerId": 40371, "position": "CENTRAL_MIDFIELD", "positionSide": "CENTRE_LEFT"}, {"playerId": 49346, "position": "DEFENSE_MIDFIELD", "positionSide": "CENTRE"}, {"playerId": 53196, "position": "RIGHT_WINGER", "positionSide": "RIGHT"}, {"playerId": 56070, "position": "GOALKEEPER", "positionSide": "CENTRE"}, {"playerId": 67636, "position": "LEFT_WINGBACK_DEFENDER", "positionSide": "LEFT"}, {"playerId": 215731, "position": "CENTRAL_DEFENDER", "positionSide": "CENTRE_LEFT"}], "substitutions": [{"gameTime": {"gameTime": "59:00.4250", "gameTimeInSec": 10840.425}, "playerId": 262, "toPosition": "RIGHT_WINGER", "positionSide": "RIGHT", "fromPosition": "LEFT_WINGER", "fromPositionSide": "LEFT", "exchangedPlayerId": null, "substitutionType": "POSITION_CHANGE"}, {"gameTime": {"gameTime": "59:00.4250", "gameTimeInSec": 10840.425}, "playerId": 53196, "toPosition": "BANK", "positionSide": "UNKNOWN", "fromPosition": "RIGHT_WINGER", "fromPositionSide": "RIGHT", "exchangedPlayerId": 68270, "substitutionType": "SUB_OFF"}, {"gameTime": {"gameTime": "59:00.4250", "gameTimeInSec": 10840.425}, "playerId": 68270, "toPosition": "LEFT_WINGER", "positionSide": "LEFT", "fromPosition": "BANK", "fromPositionSide": "UNKNOWN", "exchangedPlayerId": 53196, "substitutionType": "SUB_ON"}, {"gameTime": {"gameTime": "64:27.8500", "gameTimeInSec": 11167.85}, "playerId": 20014, "toPosition": "LEFT_WINGBACK_DEFENDER", "positionSide": "LEFT", "fromPosition": "BANK", "fromPositionSide": "UNKNOWN", "exchangedPlayerId": 67636, "substitutionType": "SUB_ON"}, {"gameTime": {"gameTime": "64:27.8500", "gameTimeInSec": 11167.85}, "playerId": 67636, "toPosition": "BANK", "positionSide": "UNKNOWN", "fromPosition": "LEFT_WINGBACK_DEFENDER", "fromPositionSide": "LEFT", "exchangedPlayerId": 20014, "substitutionType": "SUB_OFF"}, {"gameTime": {"gameTime": "84:28.7550", "gameTimeInSec": 12368.755}, "playerId": 262, "toPosition": "BANK", "positionSide": "UNKNOWN", "fromPosition": "RIGHT_WINGER", "fromPositionSide": "RIGHT", "exchangedPlayerId": 30666, "substitutionType": "SUB_OFF"}, {"gameTime": {"gameTime": "84:28.7550", "gameTimeInSec": 12368.755}, "playerId": 609, "toPosition": "BANK", "positionSide": "UNKNOWN", "fromPosition": "RIGHT_WINGBACK_DEFENDER", "fromPositionSide": "RIGHT", "exchangedPlayerId": 107198, "substitutionType": "SUB_OFF"}, {"gameTime": {"gameTime": "84:28.7550", "gameTimeInSec": 12368.755}, "playerId": 30666, "toPosition": "RIGHT_WINGER", "positionSide": "RIGHT", "fromPosition": "BANK", "fromPositionSide": "UNKNOWN", "exchangedPlayerId": 262, "substitutionType": "SUB_ON"}, {"gameTime": {"gameTime": "84:28.7550", "gameTimeInSec": 12368.755}, "playerId": 49346, "toPosition": "BANK", "positionSide": "UNKNOWN", "fromPosition": "DEFENSE_MIDFIELD", "fromPositionSide": "CENTRE", "exchangedPlayerId": 137991, "substitutionType": "SUB_OFF"}, {"gameTime": {"gameTime": "84:28.7550", "gameTimeInSec": 12368.755}, "playerId": 107198, "toPosition": "RIGHT_WINGBACK_DEFENDER", "positionSide": "RIGHT", "fromPosition": "BANK", "fromPositionSide": "UNKNOWN", "exchangedPlayerId": 609, "substitutionType": "SUB_ON"}, {"gameTime": {"gameTime": "84:28.7550", "gameTimeInSec": 12368.755}, "playerId": 137991, "toPosition": "DEFENSE_MIDFIELD", "positionSide": "CENTRE", "fromPosition": "BANK", "fromPositionSide": "UNKNOWN", "exchangedPlayerId": 49346, "substitutionType": "SUB_ON"}], "startingFormation": "4-3-3", "formations": [{"gameTime": "00:00.0000", "gameTimeInSec": 0.0, "formation": "4-3-3"}], "coachId": 11379}, "stadiumId": 5440}, "status": 200, "message": "READ_MATCH"}