{"data": {"squadHome": {"id": 1695, "players": [{"id": 21338, "position": "GOALKEEPER", "playDuration": 5849.6353, "matchShare": 1.0, "kpis": [{"kpiId": 0, "value": 10.0}, {"kpiId": 1, "value": 6.0}, {"kpiId": 3, "value": 10.0}, {"kpiId": 15, "value": 20.0}, {"kpiId": 18, "value": 5849.64}, {"kpiId": 19, "value": 1.0}, {"kpiId": 20, "value": 0.36}, {"kpiId": 21, "value": 4.7}, {"kpiId": 22, "value": 8.0}, {"kpiId": 23, "value": 16.5}, {"kpiId": 27, "value": 9.0}, {"kpiId": 29, "value": 3.8}, {"kpiId": 36, "value": 2.2}, {"kpiId": 92, "value": 24.0}, {"kpiId": 93, "value": 9.0}, {"kpiId": 1399, "value": 15.0}, {"kpiId": 1432, "value": 154.37}, {"kpiId": 1460, "value": 1.0}, {"kpiId": 1708, "value": 3796.59}]}]}, "squadAway": {"id": 805, "players": [{"id": 5911, "position": "GOALKEEPER", "playDuration": 5849.6353, "matchShare": 1.0, "kpis": [{"kpiId": 0, "value": 15.59}, {"kpiId": 1, "value": 14.0}, {"kpiId": 2, "value": 0.4}, {"kpiId": 3, "value": 15.7}, {"kpiId": 4, "value": 0.4}, {"kpiId": 6, "value": 6.48}, {"kpiId": 15, "value": 5.0}, {"kpiId": 18, "value": 5849.64}, {"kpiId": 19, "value": 1.0}, {"kpiId": 20, "value": 6.93}, {"kpiId": 21, "value": 14.17}, {"kpiId": 22, "value": 15.0}, {"kpiId": 23, "value": 15.0}, {"kpiId": 24, "value": 6.0}, {"kpiId": 27, "value": 11.0}, {"kpiId": 29, "value": 5.52}, {"kpiId": 36, "value": 1.0}, {"kpiId": 92, "value": 7.0}, {"kpiId": 93, "value": 11.0}, {"kpiId": 1399, "value": 38.0}, {"kpiId": 1400, "value": 3.0}, {"kpiId": 1432, "value": 204.71}, {"kpiId": 1460, "value": 1.0}, {"kpiId": 1708, "value": 3796.59}]}]}}}