{"data": {"id": 165176, "dateTime": "2024-11-02T16:00:00Z", "lastCalculationDate": "2025-10-15T15:02:24.017370Z", "iterationId": 1025, "squadHome": {"id": 1704, "players": [{"id": 4879, "shirtNumber": 22}, {"id": 5214, "shirtNumber": 14}, {"id": 9433, "shirtNumber": 11}, {"id": 9692, "shirtNumber": 5}, {"id": 10554, "shirtNumber": 28}, {"id": 10637, "shirtNumber": 10}, {"id": 22986, "shirtNumber": 30}, {"id": 28017, "shirtNumber": 18}, {"id": 44829, "shirtNumber": 29}, {"id": 48552, "shirtNumber": 2}, {"id": 49406, "shirtNumber": 6}, {"id": 52319, "shirtNumber": 26}, {"id": 53523, "shirtNumber": 44}, {"id": 53959, "shirtNumber": 4}, {"id": 70599, "shirtNumber": 9}, {"id": 78822, "shirtNumber": 36}, {"id": 106100, "shirtNumber": 3}, {"id": 112212, "shirtNumber": 35}], "startingPositions": [{"playerId": 4879, "position": "RIGHT_WINGBACK_DEFENDER", "positionSide": "RIGHT"}, {"playerId": 9433, "position": "CENTER_FORWARD", "positionSide": "CENTRE"}, {"playerId": 9692, "position": "CENTRAL_DEFENDER", "positionSide": "CENTRE_RIGHT"}, {"playerId": 10554, "position": "GOALKEEPER", "positionSide": "CENTRE"}, {"playerId": 10637, "position": "ATTACKING_MIDFIELD", "positionSide": "CENTRE"}, {"playerId": 22986, "position": "RIGHT_WINGER", "positionSide": "RIGHT"}, {"playerId": 28017, "position": "DEFENSE_MIDFIELD", "positionSide": "CENTRE_RIGHT"}, {"playerId": 44829, "position": "LEFT_WINGER", "positionSide": "LEFT"}, {"playerId": 48552, "position": "LEFT_WINGBACK_DEFENDER", "positionSide": "LEFT"}, {"playerId": 49406, "position": "DEFENSE_MIDFIELD", "positionSide": "CENTRE_LEFT"}, {"playerId": 52319, "position": "CENTRAL_DEFENDER", "positionSide": "CENTRE_LEFT"}], "substitutions": [{"gameTime": {"gameTime": "59:15.8370", "gameTimeInSec": 10855.837}, "playerId": 5214, "toPosition": "LEFT_WINGER", "positionSide": "LEFT", "fromPosition": "BANK", "fromPositionSide": "UNKNOWN", "exchangedPlayerId": 44829, "substitutionType": "SUB_ON"}, {"gameTime": {"gameTime": "59:15.8370", "gameTimeInSec": 10855.837}, "playerId": 44829, "toPosition": "BANK", "positionSide": "UNKNOWN", "fromPosition": "LEFT_WINGER", "fromPositionSide": "LEFT", "exchangedPlayerId": 5214, "substitutionType": "SUB_OFF"}, {"gameTime": {"gameTime": "65:43.9450", "gameTimeInSec": 11243.945}, "playerId": 9433, "toPosition": "BANK", "positionSide": "UNKNOWN", "fromPosition": "CENTER_FORWARD", "fromPositionSide": "CENTRE", "exchangedPlayerId": 70599, "substitutionType": "SUB_OFF"}, {"gameTime": {"gameTime": "65:43.9450", "gameTimeInSec": 11243.945}, "playerId": 52319, "toPosition": "BANK", "positionSide": "UNKNOWN", "fromPosition": "CENTRAL_DEFENDER", "fromPositionSide": "CENTRE_LEFT", "exchangedPlayerId": 53959, "substitutionType": "SUB_OFF"}, {"gameTime": {"gameTime": "65:43.9450", "gameTimeInSec": 11243.945}, "playerId": 53959, "toPosition": "CENTRAL_DEFENDER", "positionSide": "CENTRE_LEFT", "fromPosition": "BANK", "fromPositionSide": "UNKNOWN", "exchangedPlayerId": 52319, "substitutionType": "SUB_ON"}, {"gameTime": {"gameTime": "65:43.9450", "gameTimeInSec": 11243.945}, "playerId": 70599, "toPosition": "CENTER_FORWARD", "positionSide": "CENTRE", "fromPosition": "BANK", "fromPositionSide": "UNKNOWN", "exchangedPlayerId": 9433, "substitutionType": "SUB_ON"}, {"gameTime": {"gameTime": "81:19.6920", "gameTimeInSec": 12179.692}, "playerId": 22986, "toPosition": "DEFENSE_MIDFIELD", "positionSide": "CENTRE_RIGHT", "fromPosition": "RIGHT_WINGER", "fromPositionSide": "RIGHT", "exchangedPlayerId": null, "substitutionType": "POSITION_CHANGE"}, {"gameTime": {"gameTime": "81:19.6920", "gameTimeInSec": 12179.692}, "playerId": 28017, "toPosition": "BANK", "positionSide": "UNKNOWN", "fromPosition": "DEFENSE_MIDFIELD", "fromPositionSide": "CENTRE_RIGHT", "exchangedPlayerId": 53523, "substitutionType": "SUB_OFF"}, {"gameTime": {"gameTime": "81:19.6920", "gameTimeInSec": 12179.692}, "playerId": 53523, "toPosition": "RIGHT_WINGER", "positionSide": "RIGHT", "fromPosition": "BANK", "fromPositionSide": "UNKNOWN", "exchangedPlayerId": 28017, "substitutionType": "SUB_ON"}], "startingFormation": "4-2-3-1", "formations": [{"gameTime": "00:00.0000", "gameTimeInSec": 0.0, "formation": "4-2-3-1"}], "coachId": 3173}, "squadAway": {"id": 1701, "players": [{"id": 1251, "shirtNumber": 10}, {"id": 8896, "shirtNumber": 27}, {"id": 44756, "shirtNumber": 5}, {"id": 44770, "shirtNumber": 1}, {"id": 44792, "shirtNumber": 23}, {"id": 44835, "shirtNumber": 28}, {"id": 44843, "shirtNumber": 20}, {"id": 63300, "shirtNumber": 21}, {"id": 66029, "shirtNumber": 4}, {"id": 67818, "shirtNumber": 14}, {"id": 105204, "shirtNumber": 2}, {"id": 116076, "shirtNumber": 61}, {"id": 116092, "shirtNumber": 9}, {"id": 116818, "shirtNumber": 6}, {"id": 121125, "shirtNumber": 11}, {"id": 126960, "shirtNumber": 77}, {"id": 217192, "shirtNumber": 18}, {"id": 219818, "shirtNumber": 22}], "startingPositions": [{"playerId": 1251, "position": "ATTACKING_MIDFIELD", "positionSide": "CENTRE_RIGHT"}, {"playerId": 8896, "position": "ATTACKING_MIDFIELD", "positionSide": "CENTRE_LEFT"}, {"playerId": 44770, "position": "GOALKEEPER", "positionSide": "CENTRE"}, {"playerId": 44792, "position": "DEFENSE_MIDFIELD", "positionSide": "CENTRE_RIGHT"}, {"playerId": 44835, "position": "RIGHT_WINGBACK_DEFENDER", "positionSide": "RIGHT"}, {"playerId": 44843, "position": "LEFT_WINGBACK_DEFENDER", "positionSide": "LEFT"}, {"playerId": 66029, "position": "DEFENSE_MIDFIELD", "positionSide": "CENTRE_LEFT"}, {"playerId": 67818, "position": "CENTRAL_DEFENDER", "positionSide": "CENTRE"}, {"playerId": 116092, "position": "CENTER_FORWARD", "positionSide": "CENTRE"}, {"playerId": 116818, "position": "CENTRAL_DEFENDER", "positionSide": "CENTRE_LEFT"}, {"playerId": 217192, "position": "CENTRAL_DEFENDER", "positionSide": "CENTRE_RIGHT"}], "substitutions": [{"gameTime": {"gameTime": "68:58.0990", "gameTimeInSec": 11438.099}, "playerId": 1251, "toPosition": "CENTER_FORWARD", "positionSide": "CENTRE", "fromPosition": "ATTACKING_MIDFIELD", "fromPositionSide": "CENTRE_RIGHT", "exchangedPlayerId": null, "substitutionType": "POSITION_CHANGE"}, {"gameTime": {"gameTime": "68:58.0990", "gameTimeInSec": 11438.099}, "playerId": 116092, "toPosition": "BANK", "positionSide": "UNKNOWN", "fromPosition": "CENTER_FORWARD", "fromPositionSide": "CENTRE", "exchangedPlayerId": 126960, "substitutionType": "SUB_OFF"}, {"gameTime": {"gameTime": "68:58.0990", "gameTimeInSec": 11438.099}, "playerId": 126960, "toPosition": "ATTACKING_MIDFIELD", "positionSide": "CENTRE_RIGHT", "fromPosition": "BANK", "fromPositionSide": "UNKNOWN", "exchangedPlayerId": 116092, "substitutionType": "SUB_ON"}, {"gameTime": {"gameTime": "75:56.7350", "gameTimeInSec": 11856.735}, "playerId": 8896, "toPosition": "BANK", "positionSide": "UNKNOWN", "fromPosition": "ATTACKING_MIDFIELD", "fromPositionSide": "CENTRE_LEFT", "exchangedPlayerId": 44756, "substitutionType": "SUB_OFF"}, {"gameTime": {"gameTime": "75:56.7350", "gameTimeInSec": 11856.735}, "playerId": 44756, "toPosition": "ATTACKING_MIDFIELD", "positionSide": "CENTRE_LEFT", "fromPosition": "BANK", "fromPositionSide": "UNKNOWN", "exchangedPlayerId": 8896, "substitutionType": "SUB_ON"}, {"gameTime": {"gameTime": "85:30.3610", "gameTimeInSec": 12430.361}, "playerId": 1251, "toPosition": "BANK", "positionSide": "UNKNOWN", "fromPosition": "CENTER_FORWARD", "fromPositionSide": "CENTRE", "exchangedPlayerId": 121125, "substitutionType": "SUB_OFF"}, {"gameTime": {"gameTime": "85:30.3610", "gameTimeInSec": 12430.361}, "playerId": 121125, "toPosition": "CENTER_FORWARD", "positionSide": "CENTRE", "fromPosition": "BANK", "fromPositionSide": "UNKNOWN", "exchangedPlayerId": 1251, "substitutionType": "SUB_ON"}], "startingFormation": "5-2-2-1", "formations": [{"gameTime": "00:00.0000", "gameTimeInSec": 0.0, "formation": "5-2-2-1"}], "coachId": 1134}}, "status": 200, "message": "READ_MATCH"}